{
  "state": "iterating",
  "issue": {
    "number": 0,
    "title": "Feature with review feedback",
    "state": "OPEN",
    "body": "## Description\n\nTest scenario for review feedback loop.\n\n## Todo\n\n- [x] Implement initial feature",
    "projectStatus": "In progress",
    "iteration": 2,
    "failures": 0,
    "assignees": ["nopo-bot"],
    "labels": ["enhancement", "triaged"],
    "subIssues": [],
    "hasSubIssues": false,
    "history": [],
    "todos": {
      "total": 1,
      "completed": 1,
      "uncheckedNonManual": 0
    },
    "pr": {
      "number": 0,
      "state": "OPEN",
      "isDraft": true,
      "title": "feat: implement initial feature",
      "baseRef": "main"
    }
  }
}
